flatiron_sweep/__init__.py
flatiron_sweep/__main__.py
flatiron_sweep/clone_repo.py
flatiron_sweep/delete_repo.py
flatiron_sweep/generate_file_tree.py
flatiron_sweep/generate_list_file.py
flatiron_sweep/get_repos.py
flatiron_sweep-0.1.1.dist-info/METADATA
flatiron_sweep-0.1.1.dist-info/WHEEL
flatiron_sweep-0.1.1.dist-info/entry_points.txt
flatiron_sweep-0.1.1.dist-info/top_level.txt
flatiron_sweep-0.1.1.dist-info/RECORD
