Metadata-Version: 2.1
Name: flatiron-sweep
Version: 0.1.1
Summary: UNKNOWN
Home-page: https://github.com/SenseiCain/flatiron_sweep
Author: SenseiCain
Author-email: UNKNOWN
License: UNKNOWN
Platform: UNKNOWN
Requires-Dist: PyGithub
Requires-Dist: gitpython
